spacy_huggingface_hub/__init__.py
spacy_huggingface_hub/__main__.py
spacy_huggingface_hub/push.py
spacy_huggingface_hub-0.0.10.dist-info/LICENSE
spacy_huggingface_hub-0.0.10.dist-info/METADATA
spacy_huggingface_hub-0.0.10.dist-info/WHEEL
spacy_huggingface_hub-0.0.10.dist-info/entry_points.txt
spacy_huggingface_hub-0.0.10.dist-info/top_level.txt
spacy_huggingface_hub-0.0.10.dist-info/RECORD
