Metadata-Version: 2.1
Name: spacy-huggingface-hub
Version: 0.0.10
Summary: Quickly push your spaCy pipelines to the Hugging Face Hub
Home-page: https://spacy.io
Author: Explosion and Hugging Face
Author-email: omar@huggingface.co
License: MIT
Classifier: Development Status :: 4 - Beta
Classifier: Environment :: Console
Classifier: Intended Audience :: Developers
Classifier: Intended Audience :: Science/Research
Classifier: Topic :: Scientific/Engineering
Classifier: Topic :: Scientific/Engineering :: Artificial Intelligence
Classifier: License :: OSI Approved :: Apache Software License
Classifier: Operating System :: OS Independent
Classifier: Programming Language :: Python :: 3
Requires-Python: >=3.6
License-File: LICENSE
Requires-Dist: huggingface-hub (>=0.8.1)
Requires-Dist: wasabi (<1.2.0,>=0.8.1)
Requires-Dist: typer (<0.8.0,>=0.3.0)
Requires-Dist: PyYAML
